basespaceapp/__init__.py
basespaceapp/app.py
basespaceapp/config.py
basespaceapp/payload.py
basespaceapp/sampleapp.py
basespaceapp-0.0.8.dist-info/DESCRIPTION.rst
basespaceapp-0.0.8.dist-info/METADATA
basespaceapp-0.0.8.dist-info/RECORD
basespaceapp-0.0.8.dist-info/WHEEL
basespaceapp-0.0.8.dist-info/metadata.json
basespaceapp-0.0.8.dist-info/top_level.txt
