Metadata-Version: 2.0
Name: basespaceapp
Version: 0.0.8
Summary: template for basespace native app.
Home-page: https://github.com/alaindomissy/basespaceapp
Author: Alain Domissy
Author-email: alaindomissy@gmail.com
License: MIT
Platform: UNKNOWN
Classifier: Development Status :: 3 - Alpha
Classifier: Topic :: Utilities
Classifier: License :: OSI Approved :: MIT License
Requires-Dist: six
